superset_hetuengine/__init__.py
superset_hetuengine/db_engine_spec.py
superset_hetuengine/sqlalchemy_dialect.py
superset_hetuengine/utils.py
superset_hetuengine_connector-0.1.13.dist-info/licenses/LICENSE
superset_hetuengine_connector-0.1.13.dist-info/METADATA
superset_hetuengine_connector-0.1.13.dist-info/WHEEL
superset_hetuengine_connector-0.1.13.dist-info/entry_points.txt
superset_hetuengine_connector-0.1.13.dist-info/top_level.txt
superset_hetuengine_connector-0.1.13.dist-info/RECORD
