Metadata-Version: 2.4
Name: superset-hetuengine-connector
Version: 0.1.13
Summary: Apache Superset database connector for Huawei HetuEngine
Author: Community Contributors
License: Apache-2.0
Project-URL: Homepage, https://github.com/pesnik/superset-hetuengine-connector
Project-URL: Documentation, https://github.com/pesnik/superset-hetuengine-connector/blob/main/README.md
Project-URL: Repository, https://github.com/pesnik/superset-hetuengine-connector
Project-URL: Bug Reports, https://github.com/pesnik/superset-hetuengine-connector/issues
Project-URL: Source Code, https://github.com/pesnik/superset-hetuengine-connector
Keywords: superset,hetuengine,huawei,trino,presto,jdbc,database,connector
Classifier: Development Status :: 4 - Beta
Classifier: Intended Audience :: Developers
Classifier: Intended Audience :: System Administrators
Classifier: License :: OSI Approved :: Apache Software License
Classifier: Operating System :: OS Independent
Classifier: Programming Language :: Python :: 3
Classifier: Programming Language :: Python :: 3.10
Classifier: Programming Language :: Python :: 3.11
Classifier: Programming Language :: Python :: 3.12
Classifier: Programming Language :: Python :: 3.13
Classifier: Topic :: Database
Classifier: Topic :: Software Development :: Libraries :: Python Modules
Requires-Python: >=3.10
License-File: LICENSE
Requires-Dist: apache-superset>=5.0.0
Requires-Dist: jaydebeapi>=1.2.3
Requires-Dist: JPype1>=1.4.0
Provides-Extra: dev
Requires-Dist: pytest>=7.0.0; extra == "dev"
Requires-Dist: pytest-cov>=3.0.0; extra == "dev"
Requires-Dist: black>=22.0.0; extra == "dev"
Requires-Dist: flake8>=4.0.0; extra == "dev"
Requires-Dist: mypy>=0.950; extra == "dev"
Requires-Dist: isort>=5.10.0; extra == "dev"
Dynamic: license-file
